jupyterlab_stickyland/__init__.py
jupyterlab_stickyland/_version.py
jupyterlab_stickyland/labextension/build_log.json
jupyterlab_stickyland/labextension/package.json
jupyterlab_stickyland/labextension/static/lib_index_js.9f3820ca2e68386e67b9.js
jupyterlab_stickyland/labextension/static/lib_index_js.9f3820ca2e68386e67b9.js.map
jupyterlab_stickyland/labextension/static/remoteEntry.103b3866bb4ad3239dfa.js
jupyterlab_stickyland/labextension/static/remoteEntry.103b3866bb4ad3239dfa.js.map
jupyterlab_stickyland/labextension/static/style.js
jupyterlab_stickyland/labextension/static/style_index_js.085e5f0a3606744c9e2e.js
jupyterlab_stickyland/labextension/static/style_index_js.085e5f0a3606744c9e2e.js.map
jupyterlab_stickyland/labextension/static/vendors-node_modules_css-loader_dist_runtime_api_js-node_modules_css-loader_dist_runtime_cssW-72eba1.e38d2e3a7dc524763a25.js
jupyterlab_stickyland/labextension/static/vendors-node_modules_css-loader_dist_runtime_api_js-node_modules_css-loader_dist_runtime_cssW-72eba1.e38d2e3a7dc524763a25.js.map
jupyterlab_stickyland-0.2.4.data/data/share/jupyter/labextensions/jupyterlab-stickyland/build_log.json
jupyterlab_stickyland-0.2.4.data/data/share/jupyter/labextensions/jupyterlab-stickyland/install.json
jupyterlab_stickyland-0.2.4.data/data/share/jupyter/labextensions/jupyterlab-stickyland/package.json
jupyterlab_stickyland-0.2.4.data/data/share/jupyter/labextensions/jupyterlab-stickyland/static/lib_index_js.9f3820ca2e68386e67b9.js
jupyterlab_stickyland-0.2.4.data/data/share/jupyter/labextensions/jupyterlab-stickyland/static/lib_index_js.9f3820ca2e68386e67b9.js.map
jupyterlab_stickyland-0.2.4.data/data/share/jupyter/labextensions/jupyterlab-stickyland/static/remoteEntry.103b3866bb4ad3239dfa.js
jupyterlab_stickyland-0.2.4.data/data/share/jupyter/labextensions/jupyterlab-stickyland/static/remoteEntry.103b3866bb4ad3239dfa.js.map
jupyterlab_stickyland-0.2.4.data/data/share/jupyter/labextensions/jupyterlab-stickyland/static/style.js
jupyterlab_stickyland-0.2.4.dist-info/.ipynb_checkpoints/dependency_links-checkpoint.txt
jupyterlab_stickyland-0.2.4.dist-info/.ipynb_checkpoints/not-zip-safe-checkpoint
jupyterlab_stickyland-0.2.4.dist-info/LICENSE
jupyterlab_stickyland-0.2.4.dist-info/METADATA
jupyterlab_stickyland-0.2.4.dist-info/WHEEL
jupyterlab_stickyland-0.2.4.dist-info/top_level.txt
jupyterlab_stickyland-0.2.4.dist-info/RECORD
